README.rst
setup.py
locust_xmlrpc/__init__.py
locust_xmlrpc/transport.py
locust_xmlrpc.egg-info/PKG-INFO
locust_xmlrpc.egg-info/SOURCES.txt
locust_xmlrpc.egg-info/dependency_links.txt
locust_xmlrpc.egg-info/requires.txt
locust_xmlrpc.egg-info/top_level.txt
tests/__init__.py
tests/server.py
tests/test_transport.py