Metadata-Version: 1.0
Name: locust-xmlrpc
Version: 0.3.0
Summary: XML-RPC Transport for Locust
Home-page: https://github.com/gisce/locust-xmlrpc
Author: GISCE-TI, S.L.
Author-email: devel@gisce.net
License: MIT
Platform: UNKNOWN
